zbl-0.7.1.dist-info/METADATA
zbl-0.7.1.dist-info/WHEEL
zbl-0.7.1.dist-info/licenses/../LICENSE.txt
zbl/__init__.py
zbl/__main__.py
zbl/zbl.cp312-win_amd64.pyd
zbl-0.7.1.dist-info/RECORD
