Metadata-Version: 2.4
Name: zbl
Version: 0.7.1
Classifier: Development Status :: 4 - Beta
Classifier: Programming Language :: Rust
Classifier: Programming Language :: Python
Classifier: Programming Language :: Python :: 3
Classifier: Programming Language :: Python :: 3.9
Classifier: Programming Language :: Python :: 3.10
Classifier: Programming Language :: Python :: 3.11
Classifier: Programming Language :: Python :: 3.12
Classifier: Programming Language :: Python :: 3.13
Requires-Dist: numpy
Requires-Dist: opencv-python~=4.6.0 ; extra == 'cli'
Provides-Extra: cli
License-File: ../LICENSE.txt
Summary: real-time window capture library based on D3D11 and Windows.Graphics.Capture
Keywords: windows,d3d11,window-capture,graphics-capture,cv
Requires-Python: >=3.9
Project-URL: Homepage, https://github.com/modelflat/zbl
Project-URL: Repository, https://github.com/modelflat/zbl
